python_comrak-0.9.0.dist-info/METADATA
python_comrak-0.9.0.dist-info/WHEEL
python_comrak-0.9.0.dist-info/license_files/LICENSE.txt
python_comrak/__init__.py
python_comrak/_lowlevel.pyi
python_comrak/_lowlevel.cpython-311-x86_64-linux-gnu.so
python_comrak-0.9.0.dist-info/RECORD
