Metadata-Version: 2.1
Name: python-comrak
Version: 0.9.0
License-File: LICENSE.txt
Summary: Markdown HTML converters for Python made in Rust
Author: Merchise Autrement [~º/~] and Contributors <info@merchise.de>
Author-email: Merchise Autrement <info@merchise.de>
License: MIT
Requires-Python: >=3.8
